<?xml version="1.0" encoding="UTF-8"?>
<OpenSearchDescription xmlns="http://a9.com/-/spec/opensearch/1.1/" xmlns:moz="http://www.mozilla.org/2006/browser/search/">
  <ShortName>DRAE</ShortName>
  <Description>Diccionario de la Real Academia Española (DRAE)</Description>
  <InputEncoding>UTF-8</InputEncoding>
  <Image width="16" height="16">data:image/jpeg,%FF%D8%FF%E0%00%10JFIF%00%01%01%01%00H%00H%00%00%FF%DB%00C%00%05%03%04%04%04%03%05%04%04%04%05%05%05%06%07%0C%08%07%07%07%07%0F%0B%0B%09%0C%11%0F%12%12%11%0F%11%11%13%16%1C%17%13%14%1A%15%11%11%18!%18%1A%1D%1D%1F%1F%1F%13%17%22%24%22%1E%24%1C%1E%1F%1E%FF%DB%00C%01%05%05%05%07%06%07%0E%08%08%0E%1E%14%11%14%1E%1E%1E%1E%1E%1E%1E%1E%1E%1E%1E%1E%1E%1E%1E%1E%1E%1E%1E%1E%1E%1E%1E%1E%1E%1E%1E%1E%1E%1E%1E%1E%1E%1E%1E%1E%1E%1E%1E%1E%1E%1E%1E%1E%1E%1E%1E%1E%1E%1E%FF%C0%00%11%08%00%20%00%20%03%01%22%00%02%11%01%03%11%01%FF%C4%00%17%00%01%01%01%01%00%00%00%00%00%00%00%00%00%00%00%00%07%06%08%05%FF%C4%00*%10%00%02%02%01%02%05%04%02%02%03%00%00%00%00%00%00%01%02%03%04%11%05%12%00%06%13!1%07%22AQ%142%15%23Baq%FF%C4%00%18%01%01%00%03%01%00%00%00%00%00%00%00%00%00%00%00%00%00%01%02%05%06%FF%C4%00%1A%11%00%02%03%01%01%00%00%00%00%00%00%00%00%00%00%00%00%01%02%03%111!%FF%DA%00%0C%03%01%00%02%11%03%11%00%3F%00%D0%FC%1D%FA%A5%CC%BA%FE%94%D2%D2%8E%85t%D3f%5C%1B%1Dr%92%C9%16%DF%ED%0B%94e%04%02%DE%3B%80%BB%89%19%1C%5D%EA%D3%C9WL%B1b%26%89%5E4%C8i%3FQ%F6Oq%E0d%F7%20%7D%90%3B%81%08u%0DS%9Cg%AD6%A3r)%B4%EA%D7%96%C4T-%C5%9D%C4%96%01%8F%B4%BB%E0%82%02%A0%19%CBm%00!%DB%D0U%1Dz%F8d2%F7%D2%DEi%D7y%90%CCm%D4%0FF%00Q%AE2%18%DC%CB%D8%ED%C1%0B%9FiV%EC%BF%E5%E7%EE%F3%8C%F9%7D%F5NQ%EAZ%D3%EE%DC%83%A9jk6t%A8%15%A2%822%AA%09u%03%04%3E%7B%95%7C%92%14~%DE%EC%BA%E8%16%E4%BF%A2%D4%B9)S%24%D1%EEb%AAT%1E%E4x%3D%C1%FB%1F%07%23%BF%9E%16%C1%2FW%028%BE%A9%24%92rU%B8%93%7BG%24%91E%3A(b%5E7p%85%7D%A4%1Ce%86q%F1%E7%23%20%95%E9%06%1A%2F%3E%96%AF%23%F5%A7J%EC%ED_%A6%23GTB%1D%09%EC%81z%80%EE%DB%94%DEs%82%07%0E%D7j%D7%BBRZv%E1I%AB%CC%A5%24%8D%BC0%3F%07%82Mg%94%AEr%BE%A14%B1%D6%B9%A9%E9%16%16Ha0%D6%FC%B9bV%2C%EB%14%AAC3%26%E6s%BF%07%07ibN%D1%C5%AB%92%CC%04%FC%A7M%92%8F%F1%C0%97J%D7%1A%BCr%C2%AA%1EiGWye%93%0A%99%0C%11%D5%B3%8D%A4%12%08%2B%C2%9F%A4qM%0F%26E%14%91K%14%2Bb_%C5I%14%86%10%93%95%CE%7C%9E%E4%93%DF%24%93%F3%C1%FArf%BB%CDwj%C4t%89%B4%3D%26%B1%D9%24%B3%A4p%BFe%00%ACq%A6%18%F8%01%98%80%1Fh%C1%03%3C3%D0%A9Z%8D8%A9%D4%8B%A5%5E%15%DB%1A%02N%07%FD%3D%C9%FF%00g%CF%13l%96%60%3F%FF%D9</Image>

<!-- No suggestion service offered by DRAE's webpage -->
<Url type="text/html" method="GET" template="http://lema.rae.es/drae/">
  <Param name="val" value="{searchTerms}"/>
</Url>
<moz:SearchForm>http://lema.rae.es/drae/</moz:SearchForm>

</OpenSearchDescription>